mcp_deep_research/__init__.py
mcp_deep_research/__main__.py
mcp_deep_research/mcp_tools.py
mcp_deep_research/tools/fetcher.py
mcp_deep_research/tools/md_handler.py
mcp_deep_research/tools/read_tools.py
mcp_deep_research/tools/search_tools.py
mcp_deep_research-0.1.6.dist-info/METADATA
mcp_deep_research-0.1.6.dist-info/WHEEL
mcp_deep_research-0.1.6.dist-info/entry_points.txt
mcp_deep_research-0.1.6.dist-info/top_level.txt
mcp_deep_research-0.1.6.dist-info/RECORD
