Metadata-Version: 2.4
Name: mcp-deep-research
Version: 0.1.6
Summary: An MCP (Model-Context-Protocol) Server for Deep Academic Research
Author-email: Pb-207 <pengb0725@163.com>
License: MIT
Project-URL: Homepage, https://github.com/Pb-207/mcp-deep-research
Requires-Dist: Flask
Requires-Dist: html2text
Requires-Dist: mcp
Requires-Dist: playwright
Requires-Dist: pydantic
Requires-Dist: pyperclip
